genofunc/__init__.py
genofunc/__main__.py
genofunc/concatenate_fasta.py
genofunc/extract_metadata.py
genofunc/feature_extractor.py
genofunc/filter_fasta.py
genofunc/gene_concatenator.py
genofunc/genome_annotator.py
genofunc/genome_annotator2.py
genofunc/group_align.py
genofunc/merge.py
genofunc/name_splitter.py
genofunc/reference_matcher.py
genofunc/rename_fasta.py
genofunc/strain_encoder.py
genofunc/utils.py
genofunc/subcommands/__init__.py
genofunc/subcommands/concatenate_fasta.py
genofunc/subcommands/extract_metadata.py
genofunc/subcommands/feature_extractor.py
genofunc/subcommands/filter_fasta.py
genofunc/subcommands/gene_concatenator.py
genofunc/subcommands/genome_annotator.py
genofunc/subcommands/group_align.py
genofunc/subcommands/merge.py
genofunc/subcommands/name_splitter.py
genofunc/subcommands/reference_matcher.py
genofunc/subcommands/rename_fasta.py
genofunc/subcommands/strain_encoder.py
genofunc-1.1.3.dist-info/METADATA
genofunc-1.1.3.dist-info/WHEEL
genofunc-1.1.3.dist-info/entry_points.txt
genofunc-1.1.3.dist-info/top_level.txt
genofunc-1.1.3.dist-info/RECORD
