Metadata-Version: 2.1
Name: genofunc
Version: 1.1.3
Summary: UNKNOWN
Home-page: https://github.com/xiaoyu518/genofunc
Author: UNKNOWN
Author-email: UNKNOWN
License: MIT
Platform: UNKNOWN
Classifier: Topic :: Scientific/Engineering :: Bio-Informatics
Classifier: Programming Language :: Python :: 3 :: Only
Classifier: License :: OSI Approved :: MIT License
Requires-Dist: biopython (>=1.70)
Requires-Dist: numpy (>=1.18)
Requires-Dist: pandas (>=0.24.2)
Requires-Dist: nextstrain-augur (>=13.1.2)
Requires-Dist: mappy (>=2.24)
Requires-Dist: parasail (>=1.2.4)
